gscp/__init__.py
gscp/__main__.py
gscp/commit.py
gscp/entry.py
gscp/git.py
gscp/push_pull.py
gscp/stage.py
gscp/version.py
gscp/wrappers.py
gscp-1.0.10.dist-info/entry_points.txt
gscp-1.0.10.dist-info/LICENSE
gscp-1.0.10.dist-info/METADATA
gscp-1.0.10.dist-info/WHEEL
gscp-1.0.10.dist-info/RECORD
