Metadata-Version: 2.1
Name: gscp
Version: 1.0.10
Summary: A tool to quickly commit your work with git.
Author: Samuel Yvon
Author-email: samuelyvon9@gmail.com
Requires-Python: >=3.8,<4.0
Classifier: Programming Language :: Python :: 3
Classifier: Programming Language :: Python :: 3.8
Classifier: Programming Language :: Python :: 3.9
Classifier: Programming Language :: Python :: 3.10
Classifier: Programming Language :: Python :: 3.11
Classifier: Programming Language :: Python :: 3.12
Requires-Dist: rich (>=13.3.2,<14.0.0)
